context_packager_data/__init__.py
context_packager_data/tokenizer.py
context_packager_data/tiktoken_cache/.gitkeep
context_packager_data/tiktoken_cache/9b5ad71b2ce5302211f9c61530b329a4922fc6a4
context_packager_data/tiktoken_cache/fb374d419588a4632f3f557e76b4b70aebbca790
hr_tools/__init__.py
hr_tools/hr_instructions.md
hr_tools/package_context.py
hr_tools/pdf_to_md.py
kb/__init__.py
kb/artifacts.py
kb/create_model.py
kb/db.py
kb/eval.py
kb/gen_model.py
kb/graph.py
kb/score.py
kb/search.py
kb/train_model.py
kb/tuning.py
kb/upsert.py
resume_ui/__init__.py
resume_ui/app.py
resume_ui/cli.py
resume_ui/ingest_cli.py
resume_ui/scheduler_cli.py
resume_ui/upsert_cli.py
hr_tools/instruction.md
kb/tuning_model.json
context_packager-0.2.26.dist-info/METADATA
context_packager-0.2.26.dist-info/WHEEL
context_packager-0.2.26.dist-info/entry_points.txt
context_packager-0.2.26.dist-info/RECORD
