Metadata-Version: 2.4
Name: context-packager
Version: 0.2.26
Summary: Convert documents to Markdown (MarkItDown), package with Repomix, and serve a Streamlit UI for copyable LLM context.
Project-URL: Homepage, https://github.com/ruizmr/resume-context-builder
Author: Context Tools
License: MIT
Requires-Python: >=3.10
Requires-Dist: apscheduler==3.10.4
Requires-Dist: pdfminer-six==20250506
Requires-Dist: psycopg[binary,pool]==3.2.1
Requires-Dist: pynndescent==0.5.13
Requires-Dist: pyvis==0.3.2
Requires-Dist: repomix==0.3.4
Requires-Dist: scikit-learn==1.5.2
Requires-Dist: sqlalchemy==2.0.35
Requires-Dist: streamlit-agraph==0.0.45
Requires-Dist: streamlit==1.50.0
Requires-Dist: tiktoken==0.11.0
Provides-Extra: full
Requires-Dist: markitdown[all]==0.1.3; extra == 'full'
Requires-Dist: onnxruntime==1.23.0; (sys_platform == 'darwin') and extra == 'full'
Requires-Dist: watchdog>=4.0.0; extra == 'full'
